permeabledt/__init__.py
permeabledt/calibration.py
permeabledt/download_HRRR_historical_forecast.py
permeabledt/particle_filter.py
permeabledt/plots.py
permeabledt/water_flow_module.py
permeabledt-0.1.0.post1.dist-info/licenses/LICENSE
permeabledt-0.1.0.post1.dist-info/METADATA
permeabledt-0.1.0.post1.dist-info/WHEEL
permeabledt-0.1.0.post1.dist-info/top_level.txt
permeabledt-0.1.0.post1.dist-info/RECORD
